{
    "id": 530,
    "patch_id_row": 17,
    "patch_id_col": 20,
    "llx": 86400,
    "lly": 73440,
    "urx": 90720,
    "ury": 77760,
    "row_min": 306,
    "row_max": 324,
    "col_min": 360,
    "col_max": 378,
    "cell_density": 0.8287037037037037,
    "pin_density": 5,
    "net_density": 0.34747942386831276,
    "macro_margin": 255180,
    "RUDY_congestion": 0.000645506648771743,
    "EGR_congestion": 3.0,
    "timing": -0.577493,
    "power": 2.718499643609962e-06,
    "IR_drop": 0.0,
    "sub_nets": [
        {
            "id": 247,
            "llx": 86400,
            "lly": 73440,
            "urx": 87700,
            "ury": 77760
        },
        {
            "id": 493,
            "llx": 86400,
            "lly": 75225,
            "urx": 90720,
            "ury": 77760
        },
        {
            "id": 292,
            "llx": 86400,
            "lly": 74975,
            "urx": 90720,
            "ury": 77760
        },
        {
            "id": 291,
            "llx": 86400,
            "lly": 75046,
            "urx": 88455,
            "ury": 77760
        },
        {
            "id": 254,
            "llx": 86400,
            "lly": 75025,
            "urx": 90720,
            "ury": 77760
        }
    ],
    "patch_layer": [
        {
            "id": 0,
            "feature": {
                "wire_width": 170,
                "wire_len": 0,
                "wire_density": 0.0,
                "congestion": 0.0
            },
            "net_num": 2,
            "nets": [
                {
                    "id": 254,
                    "wire_num": 1,
                    "wires": [
                        {
                            "id": 2852,
                            "feature": {
                                "wire_len": 0
                            },
                            "path_num": 1,
                            "paths": [
                                {
                                    "id1": 167065,
                                    "x1": 88560,
                                    "y1": 74640,
                                    "real_x1": 88620,
                                    "real_y1": 74640,
                                    "r1": 311,
                                    "c1": 369,
                                    "l1": 0,
                                    "p1": 707,
                                    "id2": 167065,
                                    "x2": 88560,
                                    "y2": 74640,
                                    "real_x2": 88620,
                                    "real_y2": 74640,
                                    "r2": 311,
                                    "c2": 369,
                                    "l2": 0,
                                    "p2": 707
                                }
                            ]
                        }
                    ]
                },
                {
                    "id": 291,
                    "wire_num": 1,
                    "wires": [
                        {
                            "id": 3333,
                            "feature": {
                                "wire_len": 0
                            },
                            "path_num": 1,
                            "paths": [
                                {
                                    "id1": 167596,
                                    "x1": 87360,
                                    "y1": 74880,
                                    "real_x1": 87570,
                                    "real_y1": 75105,
                                    "r1": 312,
                                    "c1": 364,
                                    "l1": 0,
                                    "p1": 813,
                                    "id2": 167596,
                                    "x2": 87360,
                                    "y2": 74880,
                                    "real_x2": 87570,
                                    "real_y2": 75105,
                                    "r2": 312,
                                    "c2": 364,
                                    "l2": 0,
                                    "p2": 813
                                }
                            ]
                        }
                    ]
                }
            ]
        },
        {
            "id": 1,
            "feature": {
                "wire_width": 0,
                "wire_len": 0,
                "wire_density": 0.0,
                "congestion": 0.0
            },
            "net_num": 2,
            "nets": [
                {
                    "id": 254,
                    "wire_num": 1,
                    "wires": [
                        {
                            "id": 2852,
                            "feature": {
                                "wire_len": 0
                            },
                            "path_num": 1,
                            "paths": [
                                {
                                    "id1": 167065,
                                    "x1": 88560,
                                    "y1": 74640,
                                    "real_x1": 88620,
                                    "real_y1": 74640,
                                    "r1": 311,
                                    "c1": 369,
                                    "l1": 0,
                                    "p1": 707,
                                    "id2": 741657,
                                    "x2": 88560,
                                    "y2": 74640,
                                    "real_x2": 88620,
                                    "real_y2": 74640,
                                    "r2": 311,
                                    "c2": 369,
                                    "l2": 2,
                                    "p2": -1,
                                    "via": 0
                                }
                            ]
                        }
                    ]
                },
                {
                    "id": 291,
                    "wire_num": 1,
                    "wires": [
                        {
                            "id": 3333,
                            "feature": {
                                "wire_len": 0
                            },
                            "path_num": 1,
                            "paths": [
                                {
                                    "id1": 167596,
                                    "x1": 87360,
                                    "y1": 74880,
                                    "real_x1": 87570,
                                    "real_y1": 75105,
                                    "r1": 312,
                                    "c1": 364,
                                    "l1": 0,
                                    "p1": 813,
                                    "id2": 742188,
                                    "x2": 87360,
                                    "y2": 74880,
                                    "real_x2": 87570,
                                    "real_y2": 75105,
                                    "r2": 312,
                                    "c2": 364,
                                    "l2": 2,
                                    "p2": -1,
                                    "via": 0
                                }
                            ]
                        }
                    ]
                }
            ]
        },
        {
            "id": 2,
            "feature": {
                "wire_width": 140,
                "wire_len": 20640,
                "wire_density": 0.15483539094650206,
                "congestion": 1.0
            },
            "net_num": 4,
            "nets": [
                {
                    "id": 254,
                    "wire_num": 2,
                    "wires": [
                        {
                            "id": 2852,
                            "feature": {
                                "wire_len": 0
                            },
                            "path_num": 1,
                            "paths": [
                                {
                                    "id1": 741657,
                                    "x1": 88560,
                                    "y1": 74640,
                                    "real_x1": 88620,
                                    "real_y1": 74640,
                                    "r1": 311,
                                    "c1": 369,
                                    "l1": 2,
                                    "p1": -1,
                                    "id2": 741657,
                                    "x2": 88560,
                                    "y2": 74640,
                                    "real_x2": 88620,
                                    "real_y2": 74640,
                                    "r2": 311,
                                    "c2": 369,
                                    "l2": 2,
                                    "p2": -1
                                }
                            ]
                        },
                        {
                            "id": 2864,
                            "feature": {
                                "wire_len": 2160
                            },
                            "path_num": 1,
                            "paths": [
                                {
                                    "id1": 741648,
                                    "x1": 86400,
                                    "y1": 74640,
                                    "real_x1": -1,
                                    "real_y1": -1,
                                    "r1": 311,
                                    "c1": 360,
                                    "l1": 2,
                                    "p1": -1,
                                    "id2": 741657,
                                    "x2": 88560,
                                    "y2": 74640,
                                    "real_x2": 88620,
                                    "real_y2": 74640,
                                    "r2": 311,
                                    "c2": 369,
                                    "l2": 2,
                                    "p2": -1
                                }
                            ]
                        }
                    ]
                },
                {
                    "id": 291,
                    "wire_num": 7,
                    "wires": [
                        {
                            "id": 3318,
                            "feature": {
                                "wire_len": 1440
                            },
                            "path_num": 1,
                            "paths": [
                                {
                                    "id1": 742189,
                                    "x1": 87600,
                                    "y1": 74880,
                                    "real_x1": 87600,
                                    "real_y1": 75105,
                                    "r1": 312,
                                    "c1": 365,
                                    "l1": 2,
                                    "p1": -1,
                                    "id2": 742195,
                                    "x2": 89040,
                                    "y2": 74880,
                                    "real_x2": 89040,
                                    "real_y2": 75105,
                                    "r2": 312,
                                    "c2": 371,
                                    "l2": 2,
                                    "p2": -1
                                }
                            ]
                        },
                        {
                            "id": 3319,
                            "feature": {
                                "wire_len": 0
                            },
                            "path_num": 1,
                            "paths": [
                                {
                                    "id1": 747009,
                                    "x1": 86640,
                                    "y1": 77040,
                                    "real_x1": 86640,
                                    "real_y1": 77275,
                                    "r1": 321,
                                    "c1": 361,
                                    "l1": 2,
                                    "p1": -1,
                                    "id2": 747009,
                                    "x2": 86640,
                                    "y2": 77040,
                                    "real_x2": 86640,
                                    "real_y2": 77275,
                                    "r2": 321,
                                    "c2": 361,
                                    "l2": 2,
                                    "p2": -1
                                }
                            ]
                        },
                        {
                            "id": 3320,
                            "feature": {
                                "wire_len": 0
                            },
                            "path_num": 1,
                            "paths": [
                                {
                                    "id1": 742189,
                                    "x1": 87600,
                                    "y1": 74880,
                                    "real_x1": 87600,
                                    "real_y1": 75105,
                                    "r1": 312,
                                    "c1": 365,
                                    "l1": 2,
                                    "p1": -1,
                                    "id2": 742189,
                                    "x2": 87600,
                                    "y2": 74880,
                                    "real_x2": 87600,
                                    "real_y2": 75105,
                                    "r2": 312,
                                    "c2": 365,
                                    "l2": 2,
                                    "p2": -1
                                }
                            ]
                        },
                        {
                            "id": 3323,
                            "feature": {
                                "wire_len": 240
                            },
                            "path_num": 1,
                            "paths": [
                                {
                                    "id1": 742188,
                                    "x1": 87360,
                                    "y1": 74880,
                                    "real_x1": 87570,
                                    "real_y1": 75105,
                                    "r1": 312,
                                    "c1": 364,
                                    "l1": 2,
                                    "p1": -1,
                                    "id2": 742189,
                                    "x2": 87600,
                                    "y2": 74880,
                                    "real_x2": 87600,
                                    "real_y2": 75105,
                                    "r2": 312,
                                    "c2": 365,
                                    "l2": 2,
                                    "p2": -1
                                }
                            ]
                        },
                        {
                            "id": 3327,
                            "feature": {
                                "wire_len": 0
                            },
                            "path_num": 1,
                            "paths": [
                                {
                                    "id1": 742195,
                                    "x1": 89040,
                                    "y1": 74880,
                                    "real_x1": 89040,
                                    "real_y1": 75105,
                                    "r1": 312,
                                    "c1": 371,
                                    "l1": 2,
                                    "p1": -1,
                                    "id2": 742195,
                                    "x2": 89040,
                                    "y2": 74880,
                                    "real_x2": 89040,
                                    "real_y2": 75105,
                                    "r2": 312,
                                    "c2": 371,
                                    "l2": 2,
                                    "p2": -1
                                }
                            ]
                        },
                        {
                            "id": 3330,
                            "feature": {
                                "wire_len": 240
                            },
                            "path_num": 1,
                            "paths": [
                                {
                                    "id1": 747008,
                                    "x1": 86400,
                                    "y1": 77040,
                                    "real_x1": -1,
                                    "real_y1": -1,
                                    "r1": 321,
                                    "c1": 360,
                                    "l1": 2,
                                    "p1": -1,
                                    "id2": 747009,
                                    "x2": 86640,
                                    "y2": 77040,
                                    "real_x2": 86640,
                                    "real_y2": 77275,
                                    "r2": 321,
                                    "c2": 361,
                                    "l2": 2,
                                    "p2": -1
                                }
                            ]
                        },
                        {
                            "id": 3333,
                            "feature": {
                                "wire_len": 0
                            },
                            "path_num": 1,
                            "paths": [
                                {
                                    "id1": 742188,
                                    "x1": 87360,
                                    "y1": 74880,
                                    "real_x1": 87570,
                                    "real_y1": 75105,
                                    "r1": 312,
                                    "c1": 364,
                                    "l1": 2,
                                    "p1": -1,
                                    "id2": 742188,
                                    "x2": 87360,
                                    "y2": 74880,
                                    "real_x2": 87570,
                                    "real_y2": 75105,
                                    "r2": 312,
                                    "c2": 364,
                                    "l2": 2,
                                    "p2": -1
                                }
                            ]
                        }
                    ]
                },
                {
                    "id": 292,
                    "wire_num": 6,
                    "wires": [
                        {
                            "id": 3338,
                            "feature": {
                                "wire_len": 0
                            },
                            "path_num": 1,
                            "paths": [
                                {
                                    "id1": 743807,
                                    "x1": 90000,
                                    "y1": 75600,
                                    "real_x1": 90000,
                                    "real_y1": 75600,
                                    "r1": 315,
                                    "c1": 375,
                                    "l1": 2,
                                    "p1": -1,
                                    "id2": 743807,
                                    "x2": 90000,
                                    "y2": 75600,
                                    "real_x2": 90000,
                                    "real_y2": 75600,
                                    "r2": 315,
                                    "c2": 375,
                                    "l2": 2,
                                    "p2": -1
                                }
                            ]
                        },
                        {
                            "id": 3340,
                            "feature": {
                                "wire_len": 0
                            },
                            "path_num": 1,
                            "paths": [
                                {
                                    "id1": 743796,
                                    "x1": 87360,
                                    "y1": 75600,
                                    "real_x1": 87570,
                                    "real_y1": 75600,
                                    "r1": 315,
                                    "c1": 364,
                                    "l1": 2,
                                    "p1": -1,
                                    "id2": 743796,
                                    "x2": 87360,
                                    "y2": 75600,
                                    "real_x2": 87570,
                                    "real_y2": 75600,
                                    "r2": 315,
                                    "c2": 364,
                                    "l2": 2,
                                    "p2": -1
                                }
                            ]
                        },
                        {
                            "id": 3341,
                            "feature": {
                                "wire_len": 0
                            },
                            "path_num": 1,
                            "paths": [
                                {
                                    "id1": 742187,
                                    "x1": 87120,
                                    "y1": 74880,
                                    "real_x1": 87120,
                                    "real_y1": 75055,
                                    "r1": 312,
                                    "c1": 363,
                                    "l1": 2,
                                    "p1": -1,
                                    "id2": 742187,
                                    "x2": 87120,
                                    "y2": 74880,
                                    "real_x2": 87120,
                                    "real_y2": 75055,
                                    "r2": 312,
                                    "c2": 363,
                                    "l2": 2,
                                    "p2": -1
                                }
                            ]
                        },
                        {
                            "id": 3343,
                            "feature": {
                                "wire_len": 2640
                            },
                            "path_num": 1,
                            "paths": [
                                {
                                    "id1": 743796,
                                    "x1": 87360,
                                    "y1": 75600,
                                    "real_x1": 87570,
                                    "real_y1": 75600,
                                    "r1": 315,
                                    "c1": 364,
                                    "l1": 2,
                                    "p1": -1,
                                    "id2": 743807,
                                    "x2": 90000,
                                    "y2": 75600,
                                    "real_x2": 90000,
                                    "real_y2": 75600,
                                    "r2": 315,
                                    "c2": 375,
                                    "l2": 2,
                                    "p2": -1
                                }
                            ]
                        },
                        {
                            "id": 3350,
                            "feature": {
                                "wire_len": 720
                            },
                            "path_num": 1,
                            "paths": [
                                {
                                    "id1": 742184,
                                    "x1": 86400,
                                    "y1": 74880,
                                    "real_x1": -1,
                                    "real_y1": -1,
                                    "r1": 312,
                                    "c1": 360,
                                    "l1": 2,
                                    "p1": -1,
                                    "id2": 742187,
                                    "x2": 87120,
                                    "y2": 74880,
                                    "real_x2": 87120,
                                    "real_y2": 75055,
                                    "r2": 312,
                                    "c2": 363,
                                    "l2": 2,
                                    "p2": -1
                                }
                            ]
                        },
                        {
                            "id": 3354,
                            "feature": {
                                "wire_len": 720
                            },
                            "path_num": 1,
                            "paths": [
                                {
                                    "id1": 743807,
                                    "x1": 90000,
                                    "y1": 75600,
                                    "real_x1": 90000,
                                    "real_y1": 75600,
                                    "r1": 315,
                                    "c1": 375,
                                    "l1": 2,
                                    "p1": -1,
                                    "id2": 743810,
                                    "x2": 90720,
                                    "y2": 75600,
                                    "real_x2": -1,
                                    "real_y2": -1,
                                    "r2": 315,
                                    "c2": 378,
                                    "l2": 2,
                                    "p2": -1
                                }
                            ]
                        }
                    ]
                },
                {
                    "id": 493,
                    "wire_num": 1,
                    "wires": [
                        {
                            "id": 4953,
                            "feature": {
                                "wire_len": 4800
                            },
                            "path_num": 3,
                            "paths": [
                                {
                                    "id1": 744867,
                                    "x1": 87120,
                                    "y1": 76080,
                                    "real_x1": 87120,
                                    "real_y1": 76080,
                                    "r1": 317,
                                    "c1": 363,
                                    "l1": 2,
                                    "p1": -1,
                                    "id2": 744882,
                                    "x2": 90720,
                                    "y2": 76080,
                                    "real_x2": -1,
                                    "real_y2": -1,
                                    "r2": 317,
                                    "c2": 378,
                                    "l2": 2,
                                    "p2": -1
                                },
                                {
                                    "id1": 743795,
                                    "x1": 87120,
                                    "y1": 75600,
                                    "real_x1": 87120,
                                    "real_y1": 75600,
                                    "r1": 315,
                                    "c1": 363,
                                    "l1": 2,
                                    "p1": -1,
                                    "id2": 744867,
                                    "x2": 87120,
                                    "y2": 76080,
                                    "real_x2": 87120,
                                    "real_y2": 76080,
                                    "r2": 317,
                                    "c2": 363,
                                    "l2": 2,
                                    "p2": -1
                                },
                                {
                                    "id1": 743792,
                                    "x1": 86400,
                                    "y1": 75600,
                                    "real_x1": -1,
                                    "real_y1": -1,
                                    "r1": 315,
                                    "c1": 360,
                                    "l1": 2,
                                    "p1": -1,
                                    "id2": 743795,
                                    "x2": 87120,
                                    "y2": 75600,
                                    "real_x2": 87120,
                                    "real_y2": 75600,
                                    "r2": 315,
                                    "c2": 363,
                                    "l2": 2,
                                    "p2": -1
                                }
                            ]
                        }
                    ]
                }
            ]
        },
        {
            "id": 3,
            "feature": {
                "wire_width": 0,
                "wire_len": 0,
                "wire_density": 0.0,
                "congestion": 0.0
            },
            "net_num": 2,
            "nets": [
                {
                    "id": 291,
                    "wire_num": 3,
                    "wires": [
                        {
                            "id": 3319,
                            "feature": {
                                "wire_len": 0
                            },
                            "path_num": 1,
                            "paths": [
                                {
                                    "id1": 747009,
                                    "x1": 86640,
                                    "y1": 77040,
                                    "real_x1": 86640,
                                    "real_y1": 77275,
                                    "r1": 321,
                                    "c1": 361,
                                    "l1": 2,
                                    "p1": -1,
                                    "id2": 1321601,
                                    "x2": 86640,
                                    "y2": 77040,
                                    "real_x2": 86640,
                                    "real_y2": 77275,
                                    "r2": 321,
                                    "c2": 361,
                                    "l2": 4,
                                    "p2": -1,
                                    "via": 5
                                }
                            ]
                        },
                        {
                            "id": 3320,
                            "feature": {
                                "wire_len": 0
                            },
                            "path_num": 1,
                            "paths": [
                                {
                                    "id1": 742189,
                                    "x1": 87600,
                                    "y1": 74880,
                                    "real_x1": 87600,
                                    "real_y1": 75105,
                                    "r1": 312,
                                    "c1": 365,
                                    "l1": 2,
                                    "p1": -1,
                                    "id2": 1316781,
                                    "x2": 87600,
                                    "y2": 74880,
                                    "real_x2": 87600,
                                    "real_y2": 75105,
                                    "r2": 312,
                                    "c2": 365,
                                    "l2": 4,
                                    "p2": -1,
                                    "via": 5
                                }
                            ]
                        },
                        {
                            "id": 3327,
                            "feature": {
                                "wire_len": 0
                            },
                            "path_num": 1,
                            "paths": [
                                {
                                    "id1": 742195,
                                    "x1": 89040,
                                    "y1": 74880,
                                    "real_x1": 89040,
                                    "real_y1": 75105,
                                    "r1": 312,
                                    "c1": 371,
                                    "l1": 2,
                                    "p1": -1,
                                    "id2": 1316787,
                                    "x2": 89040,
                                    "y2": 74880,
                                    "real_x2": 89040,
                                    "real_y2": 75105,
                                    "r2": 312,
                                    "c2": 371,
                                    "l2": 4,
                                    "p2": -1,
                                    "via": 5
                                }
                            ]
                        }
                    ]
                },
                {
                    "id": 292,
                    "wire_num": 3,
                    "wires": [
                        {
                            "id": 3338,
                            "feature": {
                                "wire_len": 0
                            },
                            "path_num": 1,
                            "paths": [
                                {
                                    "id1": 743807,
                                    "x1": 90000,
                                    "y1": 75600,
                                    "real_x1": 90000,
                                    "real_y1": 75600,
                                    "r1": 315,
                                    "c1": 375,
                                    "l1": 2,
                                    "p1": -1,
                                    "id2": 1318399,
                                    "x2": 90000,
                                    "y2": 75600,
                                    "real_x2": 90000,
                                    "real_y2": 75600,
                                    "r2": 315,
                                    "c2": 375,
                                    "l2": 4,
                                    "p2": -1,
                                    "via": 5
                                }
                            ]
                        },
                        {
                            "id": 3340,
                            "feature": {
                                "wire_len": 0
                            },
                            "path_num": 1,
                            "paths": [
                                {
                                    "id1": 743796,
                                    "x1": 87360,
                                    "y1": 75600,
                                    "real_x1": 87570,
                                    "real_y1": 75600,
                                    "r1": 315,
                                    "c1": 364,
                                    "l1": 2,
                                    "p1": -1,
                                    "id2": 1318388,
                                    "x2": 87360,
                                    "y2": 75600,
                                    "real_x2": 87570,
                                    "real_y2": 75600,
                                    "r2": 315,
                                    "c2": 364,
                                    "l2": 4,
                                    "p2": -1,
                                    "via": 5
                                }
                            ]
                        },
                        {
                            "id": 3341,
                            "feature": {
                                "wire_len": 0
                            },
                            "path_num": 1,
                            "paths": [
                                {
                                    "id1": 742187,
                                    "x1": 87120,
                                    "y1": 74880,
                                    "real_x1": 87120,
                                    "real_y1": 75055,
                                    "r1": 312,
                                    "c1": 363,
                                    "l1": 2,
                                    "p1": -1,
                                    "id2": 1316779,
                                    "x2": 87120,
                                    "y2": 74880,
                                    "real_x2": 87120,
                                    "real_y2": 75055,
                                    "r2": 312,
                                    "c2": 363,
                                    "l2": 4,
                                    "p2": -1,
                                    "via": 5
                                }
                            ]
                        }
                    ]
                }
            ]
        },
        {
            "id": 4,
            "feature": {
                "wire_width": 140,
                "wire_len": 25680,
                "wire_density": 0.1926440329218107,
                "congestion": 2.0
            },
            "net_num": 3,
            "nets": [
                {
                    "id": 247,
                    "wire_num": 1,
                    "wires": [
                        {
                            "id": 2677,
                            "feature": {
                                "wire_len": 4800
                            },
                            "path_num": 3,
                            "paths": [
                                {
                                    "id1": 1315175,
                                    "x1": 88080,
                                    "y1": 74160,
                                    "real_x1": 88080,
                                    "real_y1": 74160,
                                    "r1": 309,
                                    "c1": 367,
                                    "l1": 4,
                                    "p1": -1,
                                    "id2": 1323215,
                                    "x2": 88080,
                                    "y2": 77760,
                                    "real_x2": -1,
                                    "real_y2": -1,
                                    "r2": 324,
                                    "c2": 367,
                                    "l2": 4,
                                    "p2": -1
                                },
                                {
                                    "id1": 1315173,
                                    "x1": 87600,
                                    "y1": 74160,
                                    "real_x1": 87600,
                                    "real_y1": 74160,
                                    "r1": 309,
                                    "c1": 365,
                                    "l1": 4,
                                    "p1": -1,
                                    "id2": 1315175,
                                    "x2": 88080,
                                    "y2": 74160,
                                    "real_x2": 88080,
                                    "real_y2": 74160,
                                    "r2": 309,
                                    "c2": 367,
                                    "l2": 4,
                                    "p2": -1
                                },
                                {
                                    "id1": 1313565,
                                    "x1": 87600,
                                    "y1": 73440,
                                    "real_x1": -1,
                                    "real_y1": -1,
                                    "r1": 306,
                                    "c1": 365,
                                    "l1": 4,
                                    "p1": -1,
                                    "id2": 1315173,
                                    "x2": 87600,
                                    "y2": 74160,
                                    "real_x2": 87600,
                                    "real_y2": 74160,
                                    "r2": 309,
                                    "c2": 365,
                                    "l2": 4,
                                    "p2": -1
                                }
                            ]
                        }
                    ]
                },
                {
                    "id": 291,
                    "wire_num": 5,
                    "wires": [
                        {
                            "id": 3319,
                            "feature": {
                                "wire_len": 0
                            },
                            "path_num": 1,
                            "paths": [
                                {
                                    "id1": 1321601,
                                    "x1": 86640,
                                    "y1": 77040,
                                    "real_x1": 86640,
                                    "real_y1": 77275,
                                    "r1": 321,
                                    "c1": 361,
                                    "l1": 4,
                                    "p1": -1,
                                    "id2": 1321601,
                                    "x2": 86640,
                                    "y2": 77040,
                                    "real_x2": 86640,
                                    "real_y2": 77275,
                                    "r2": 321,
                                    "c2": 361,
                                    "l2": 4,
                                    "p2": -1
                                }
                            ]
                        },
                        {
                            "id": 3320,
                            "feature": {
                                "wire_len": 0
                            },
                            "path_num": 1,
                            "paths": [
                                {
                                    "id1": 1316781,
                                    "x1": 87600,
                                    "y1": 74880,
                                    "real_x1": 87600,
                                    "real_y1": 75105,
                                    "r1": 312,
                                    "c1": 365,
                                    "l1": 4,
                                    "p1": -1,
                                    "id2": 1316781,
                                    "x2": 87600,
                                    "y2": 74880,
                                    "real_x2": 87600,
                                    "real_y2": 75105,
                                    "r2": 312,
                                    "c2": 365,
                                    "l2": 4,
                                    "p2": -1
                                }
                            ]
                        },
                        {
                            "id": 3327,
                            "feature": {
                                "wire_len": 0
                            },
                            "path_num": 1,
                            "paths": [
                                {
                                    "id1": 1316787,
                                    "x1": 89040,
                                    "y1": 74880,
                                    "real_x1": 89040,
                                    "real_y1": 75105,
                                    "r1": 312,
                                    "c1": 371,
                                    "l1": 4,
                                    "p1": -1,
                                    "id2": 1316787,
                                    "x2": 89040,
                                    "y2": 74880,
                                    "real_x2": 89040,
                                    "real_y2": 75105,
                                    "r2": 312,
                                    "c2": 371,
                                    "l2": 4,
                                    "p2": -1
                                }
                            ]
                        },
                        {
                            "id": 3328,
                            "feature": {
                                "wire_len": 2880
                            },
                            "path_num": 1,
                            "paths": [
                                {
                                    "id1": 1316787,
                                    "x1": 89040,
                                    "y1": 74880,
                                    "real_x1": 89040,
                                    "real_y1": 75105,
                                    "r1": 312,
                                    "c1": 371,
                                    "l1": 4,
                                    "p1": -1,
                                    "id2": 1323219,
                                    "x2": 89040,
                                    "y2": 77760,
                                    "real_x2": -1,
                                    "real_y2": -1,
                                    "r2": 324,
                                    "c2": 371,
                                    "l2": 4,
                                    "p2": -1
                                }
                            ]
                        },
                        {
                            "id": 3336,
                            "feature": {
                                "wire_len": 3600
                            },
                            "path_num": 3,
                            "paths": [
                                {
                                    "id1": 1316245,
                                    "x1": 87600,
                                    "y1": 74640,
                                    "real_x1": 87600,
                                    "real_y1": 74640,
                                    "r1": 311,
                                    "c1": 365,
                                    "l1": 4,
                                    "p1": -1,
                                    "id2": 1316781,
                                    "x2": 87600,
                                    "y2": 74880,
                                    "real_x2": 87600,
                                    "real_y2": 75105,
                                    "r2": 312,
                                    "c2": 365,
                                    "l2": 4,
                                    "p2": -1
                                },
                                {
                                    "id1": 1316241,
                                    "x1": 86640,
                                    "y1": 74640,
                                    "real_x1": 86640,
                                    "real_y1": 74640,
                                    "r1": 311,
                                    "c1": 361,
                                    "l1": 4,
                                    "p1": -1,
                                    "id2": 1316245,
                                    "x2": 87600,
                                    "y2": 74640,
                                    "real_x2": 87600,
                                    "real_y2": 74640,
                                    "r2": 311,
                                    "c2": 365,
                                    "l2": 4,
                                    "p2": -1
                                },
                                {
                                    "id1": 1316241,
                                    "x1": 86640,
                                    "y1": 74640,
                                    "real_x1": 86640,
                                    "real_y1": 74640,
                                    "r1": 311,
                                    "c1": 361,
                                    "l1": 4,
                                    "p1": -1,
                                    "id2": 1321601,
                                    "x2": 86640,
                                    "y2": 77040,
                                    "real_x2": 86640,
                                    "real_y2": 77275,
                                    "r2": 321,
                                    "c2": 361,
                                    "l2": 4,
                                    "p2": -1
                                }
                            ]
                        }
                    ]
                },
                {
                    "id": 292,
                    "wire_num": 7,
                    "wires": [
                        {
                            "id": 3338,
                            "feature": {
                                "wire_len": 0
                            },
                            "path_num": 1,
                            "paths": [
                                {
                                    "id1": 1318399,
                                    "x1": 90000,
                                    "y1": 75600,
                                    "real_x1": 90000,
                                    "real_y1": 75600,
                                    "r1": 315,
                                    "c1": 375,
                                    "l1": 4,
                                    "p1": -1,
                                    "id2": 1318399,
                                    "x2": 90000,
                                    "y2": 75600,
                                    "real_x2": 90000,
                                    "real_y2": 75600,
                                    "r2": 315,
                                    "c2": 375,
                                    "l2": 4,
                                    "p2": -1
                                }
                            ]
                        },
                        {
                            "id": 3339,
                            "feature": {
                                "wire_len": 240
                            },
                            "path_num": 1,
                            "paths": [
                                {
                                    "id1": 1318387,
                                    "x1": 87120,
                                    "y1": 75600,
                                    "real_x1": 87120,
                                    "real_y1": 75600,
                                    "r1": 315,
                                    "c1": 363,
                                    "l1": 4,
                                    "p1": -1,
                                    "id2": 1318388,
                                    "x2": 87360,
                                    "y2": 75600,
                                    "real_x2": 87570,
                                    "real_y2": 75600,
                                    "r2": 315,
                                    "c2": 364,
                                    "l2": 4,
                                    "p2": -1
                                }
                            ]
                        },
                        {
                            "id": 3340,
                            "feature": {
                                "wire_len": 0
                            },
                            "path_num": 1,
                            "paths": [
                                {
                                    "id1": 1318388,
                                    "x1": 87360,
                                    "y1": 75600,
                                    "real_x1": 87570,
                                    "real_y1": 75600,
                                    "r1": 315,
                                    "c1": 364,
                                    "l1": 4,
                                    "p1": -1,
                                    "id2": 1318388,
                                    "x2": 87360,
                                    "y2": 75600,
                                    "real_x2": 87570,
                                    "real_y2": 75600,
                                    "r2": 315,
                                    "c2": 364,
                                    "l2": 4,
                                    "p2": -1
                                }
                            ]
                        },
                        {
                            "id": 3341,
                            "feature": {
                                "wire_len": 0
                            },
                            "path_num": 1,
                            "paths": [
                                {
                                    "id1": 1316779,
                                    "x1": 87120,
                                    "y1": 74880,
                                    "real_x1": 87120,
                                    "real_y1": 75055,
                                    "r1": 312,
                                    "c1": 363,
                                    "l1": 4,
                                    "p1": -1,
                                    "id2": 1316779,
                                    "x2": 87120,
                                    "y2": 74880,
                                    "real_x2": 87120,
                                    "real_y2": 75055,
                                    "r2": 312,
                                    "c2": 363,
                                    "l2": 4,
                                    "p2": -1
                                }
                            ]
                        },
                        {
                            "id": 3344,
                            "feature": {
                                "wire_len": 720
                            },
                            "path_num": 1,
                            "paths": [
                                {
                                    "id1": 1316779,
                                    "x1": 87120,
                                    "y1": 74880,
                                    "real_x1": 87120,
                                    "real_y1": 75055,
                                    "r1": 312,
                                    "c1": 363,
                                    "l1": 4,
                                    "p1": -1,
                                    "id2": 1318387,
                                    "x2": 87120,
                                    "y2": 75600,
                                    "real_x2": 87120,
                                    "real_y2": 75600,
                                    "r2": 315,
                                    "c2": 363,
                                    "l2": 4,
                                    "p2": -1
                                }
                            ]
                        },
                        {
                            "id": 3346,
                            "feature": {
                                "wire_len": 2160
                            },
                            "path_num": 1,
                            "paths": [
                                {
                                    "id1": 1318399,
                                    "x1": 90000,
                                    "y1": 75600,
                                    "real_x1": 90000,
                                    "real_y1": 75600,
                                    "r1": 315,
                                    "c1": 375,
                                    "l1": 4,
                                    "p1": -1,
                                    "id2": 1323223,
                                    "x2": 90000,
                                    "y2": 77760,
                                    "real_x2": -1,
                                    "real_y2": -1,
                                    "r2": 324,
                                    "c2": 375,
                                    "l2": 4,
                                    "p2": -1
                                }
                            ]
                        },
                        {
                            "id": 3347,
                            "feature": {
                                "wire_len": 2160
                            },
                            "path_num": 1,
                            "paths": [
                                {
                                    "id1": 1318387,
                                    "x1": 87120,
                                    "y1": 75600,
                                    "real_x1": 87120,
                                    "real_y1": 75600,
                                    "r1": 315,
                                    "c1": 363,
                                    "l1": 4,
                                    "p1": -1,
                                    "id2": 1323211,
                                    "x2": 87120,
                                    "y2": 77760,
                                    "real_x2": -1,
                                    "real_y2": -1,
                                    "r2": 324,
                                    "c2": 363,
                                    "l2": 4,
                                    "p2": -1
                                }
                            ]
                        }
                    ]
                }
            ]
        },
        {
            "id": 5,
            "feature": {
                "wire_width": 0,
                "wire_len": 0,
                "wire_density": 0.0,
                "congestion": 0.0
            },
            "net_num": 0,
            "nets": []
        },
        {
            "id": 6,
            "feature": {
                "wire_width": 300,
                "wire_len": 0,
                "wire_density": 0.0,
                "congestion": 0.0
            },
            "net_num": 0,
            "nets": []
        },
        {
            "id": 7,
            "feature": {
                "wire_width": 0,
                "wire_len": 0,
                "wire_density": 0.0,
                "congestion": 0.0
            },
            "net_num": 0,
            "nets": []
        },
        {
            "id": 8,
            "feature": {
                "wire_width": 300,
                "wire_len": 0,
                "wire_density": 0.0,
                "congestion": 0.0
            },
            "net_num": 0,
            "nets": []
        },
        {
            "id": 9,
            "feature": {
                "wire_width": 0,
                "wire_len": 0,
                "wire_density": 0.0,
                "congestion": 0.0
            },
            "net_num": 0,
            "nets": []
        },
        {
            "id": 10,
            "feature": {
                "wire_width": 1600,
                "wire_len": 0,
                "wire_density": 0.0,
                "congestion": 0.0
            },
            "net_num": 0,
            "nets": []
        }
    ]
}