[
    {
        "node_0": {
            "Point": "dpath/b_reg/_133_:CLK (sky130_fd_sc_hs__dfxtp_1)",
            "Capacitance": 0.003,
            "slew": 0.0,
            "trans_type": "fall"
        }
    },
    {
        "inst_arc_0": {
            "Incr": 0.233984
        }
    },
    {
        "node_1": {
            "Point": "dpath/b_reg/_133_:Q (sky130_fd_sc_hs__dfxtp_1)",
            "Capacitance": 0.018436121989760006,
            "slew": 0.074571,
            "trans_type": "fall"
        }
    },
    {
        "net_arc_1": {
            "Incr": 0.000135,
            "edge_0": {
                "wire_from_node": "dpath/b_reg/_133_:Q",
                "wire_to_node": "dpath/a_lt_b$in1[1]:609584",
                "wire_R": 0.0,
                "wire_C": 0.0,
                "from_slew": 0.13417,
                "to_slew": 0.13417,
                "wire_delay": 0.0
            },
            "edge_1": {
                "wire_from_node": "dpath/a_lt_b$in1[1]:609584",
                "wire_to_node": "dpath/a_lt_b$in1[1]:609575",
                "wire_R": 1.9285714285714286,
                "wire_C": 9.720179408000129e-05,
                "from_slew": 0.13417,
                "to_slew": 0.13417008961665514,
                "wire_delay": 3.536791752024001e-05
            },
            "edge_2": {
                "wire_from_node": "dpath/a_lt_b$in1[1]:609575",
                "wire_to_node": "dpath/a_lt_b$in1[1]:1184167",
                "wire_R": 0.0,
                "wire_C": 9.720179408000129e-05,
                "from_slew": 0.13417008961665514,
                "to_slew": 0.13417008961665514,
                "wire_delay": 0.0
            },
            "edge_3": {
                "wire_from_node": "dpath/a_lt_b$in1[1]:1184167",
                "wire_to_node": "dpath/a_lt_b$in1[1]:1195959",
                "wire_R": 4.714285714285714,
                "wire_C": 0.00021091565408000099,
                "from_slew": 0.13417008961665514,
                "to_slew": 0.1341702703581468,
                "wire_delay": 8.500235580973714e-05
            },
            "edge_4": {
                "wire_from_node": "dpath/a_lt_b$in1[1]:1195959",
                "wire_to_node": "dpath/a_lt_b$in1[1]:621367",
                "wire_R": 0.0,
                "wire_C": 0.00021091565408000099,
                "from_slew": 0.1341702703581468,
                "to_slew": 0.1341702703581468,
                "wire_delay": 0.0
            },
            "edge_5": {
                "wire_from_node": "dpath/a_lt_b$in1[1]:621367",
                "wire_to_node": "dpath/a_lt_b$in1[1]:621351",
                "wire_R": 3.428571428571428,
                "wire_C": 0.014921459290240002,
                "from_slew": 0.1341702703581468,
                "to_slew": 0.134170271067162,
                "wire_delay": 9.937466753828562e-06
            },
            "edge_6": {
                "wire_from_node": "dpath/a_lt_b$in1[1]:621351",
                "wire_to_node": "dpath/a_lt_b$in1[1]:1195943",
                "wire_R": 0.0,
                "wire_C": 0.00016838589392000015,
                "from_slew": 0.134170271067162,
                "to_slew": 0.134170271067162,
                "wire_delay": 0.0
            },
            "edge_7": {
                "wire_from_node": "dpath/a_lt_b$in1[1]:1195943",
                "wire_to_node": "dpath/a_lt_b$in1[1]:1197551",
                "wire_R": 0.6428571428571428,
                "wire_C": 3.332663192000002e-05,
                "from_slew": 0.134170271067162,
                "to_slew": 0.1341702711198998,
                "wire_delay": 1.7336026783028592e-06
            },
            "edge_8": {
                "wire_from_node": "dpath/a_lt_b$in1[1]:1197551",
                "wire_to_node": "dpath/a_lt_b$in1[1]:622959",
                "wire_R": 0.0,
                "wire_C": 3.332663192000002e-05,
                "from_slew": 0.1341702711198998,
                "to_slew": 0.1341702711198998,
                "wire_delay": 0.0
            },
            "edge_9": {
                "wire_from_node": "dpath/a_lt_b$in1[1]:622959",
                "wire_to_node": "dpath/a_lt_b$in1[1]:622953",
                "wire_R": 1.2857142857142856,
                "wire_C": 6.669432271999998e-05,
                "from_slew": 0.1341702711198998,
                "to_slew": 0.13417027116143765,
                "wire_delay": 3.3386069863542976e-06
            },
            "edge_10": {
                "wire_from_node": "dpath/a_lt_b$in1[1]:622953",
                "wire_to_node": "dpath/b_reg/_087_:A",
                "wire_R": 0.0,
                "wire_C": 6.669432271999998e-05,
                "from_slew": 0.13417027116143765,
                "to_slew": 0.13417027116143765,
                "wire_delay": 0.0
            }
        }
    },
    {
        "node_2": {
            "Point": "dpath/b_reg/_087_:A (sky130_fd_sc_hs__buf_1)",
            "Capacitance": 0.00253,
            "slew": 0.074571,
            "trans_type": "fall"
        }
    },
    {
        "inst_arc_2": {
            "Incr": 0.08584
        }
    },
    {
        "node_3": {
            "Point": "dpath/b_reg/_087_:X (sky130_fd_sc_hs__buf_1)",
            "Capacitance": 0.0038236148918399998,
            "slew": 0.02449,
            "trans_type": "fall"
        }
    },
    {
        "net_arc_3": {
            "Incr": 1.4e-05,
            "edge_0": {
                "wire_from_node": "dpath/b_reg/_087_:X",
                "wire_to_node": "dpath/b_reg/_057_:620276",
                "wire_R": 0.0,
                "wire_C": 0.0,
                "from_slew": 0.039192,
                "to_slew": 0.039192,
                "wire_delay": 0.0
            },
            "edge_1": {
                "wire_from_node": "dpath/b_reg/_057_:620276",
                "wire_to_node": "dpath/b_reg/_057_:620267",
                "wire_R": 1.9285714285714286,
                "wire_C": 9.720179407999999e-05,
                "from_slew": 0.039192,
                "to_slew": 0.03919200181137554,
                "wire_delay": 7.1866538313942854e-06
            },
            "edge_2": {
                "wire_from_node": "dpath/b_reg/_057_:620267",
                "wire_to_node": "dpath/b_reg/_057_:1194859",
                "wire_R": 0.0,
                "wire_C": 9.720179407999999e-05,
                "from_slew": 0.03919200181137554,
                "to_slew": 0.03919200181137554,
                "wire_delay": 0.0
            },
            "edge_3": {
                "wire_from_node": "dpath/b_reg/_057_:1194859",
                "wire_to_node": "dpath/b_reg/_057_:1197003",
                "wire_R": 0.857142857142857,
                "wire_C": 4.267342256000003e-05,
                "from_slew": 0.03919200181137554,
                "to_slew": 0.03919200220301511,
                "wire_delay": 3.074175326674286e-06
            },
            "edge_4": {
                "wire_from_node": "dpath/b_reg/_057_:1197003",
                "wire_to_node": "dpath/b_reg/_057_:1771595",
                "wire_R": 0.0,
                "wire_C": 4.267342256000003e-05,
                "from_slew": 0.03919200220301511,
                "to_slew": 0.03919200220301511,
                "wire_delay": 0.0
            },
            "edge_5": {
                "wire_from_node": "dpath/b_reg/_057_:1771595",
                "wire_to_node": "dpath/b_reg/_057_:1771575",
                "wire_R": 0.752,
                "wire_C": 0.00021795238799999974,
                "from_slew": 0.03919200220301511,
                "to_slew": 0.039192002361030834,
                "wire_delay": 2.50108587706112e-06
            },
            "edge_6": {
                "wire_from_node": "dpath/b_reg/_057_:1771575",
                "wire_to_node": "dpath/b_reg/_057_:1196983",
                "wire_R": 0.0,
                "wire_C": 0.00021795238800000017,
                "from_slew": 0.039192002361030834,
                "to_slew": 0.039192002361030834,
                "wire_delay": 0.0
            },
            "edge_7": {
                "wire_from_node": "dpath/b_reg/_057_:1196983",
                "wire_to_node": "dpath/b_reg/_057_:1198055",
                "wire_R": 0.4285714285714285,
                "wire_C": 2.3979841280000018e-05,
                "from_slew": 0.039192002361030834,
                "to_slew": 0.03919200238331734,
                "wire_delay": 1.321705646262857e-06
            },
            "edge_8": {
                "wire_from_node": "dpath/b_reg/_057_:1198055",
                "wire_to_node": "dpath/b_reg/_057_:623463",
                "wire_R": 0.0,
                "wire_C": 2.3979841280000018e-05,
                "from_slew": 0.03919200238331734,
                "to_slew": 0.03919200238331734,
                "wire_delay": 0.0
            },
            "edge_9": {
                "wire_from_node": "dpath/b_reg/_057_:623463",
                "wire_to_node": "dpath/b_reg/_068_:A0",
                "wire_R": 0.0,
                "wire_C": 0.0,
                "from_slew": 0.03919200238331734,
                "to_slew": 0.03919200238331734,
                "wire_delay": 0.0
            }
        }
    },
    {
        "node_4": {
            "Point": "dpath/b_reg/_068_:A0 (sky130_fd_sc_hs__mux2_1)",
            "Capacitance": 0.00306,
            "slew": 0.02449,
            "trans_type": "fall"
        }
    },
    {
        "inst_arc_4": {
            "Incr": 0.11453
        }
    },
    {
        "node_5": {
            "Point": "dpath/b_reg/_068_:X (sky130_fd_sc_hs__mux2_1)",
            "Capacitance": 0.0028015267684800005,
            "slew": 0.030595,
            "trans_type": "fall"
        }
    },
    {
        "net_arc_5": {
            "Incr": 7e-06,
            "edge_0": {
                "wire_from_node": "dpath/b_reg/_068_:X",
                "wire_to_node": "dpath/b_reg/_023_:620255",
                "wire_R": 0.0,
                "wire_C": 0.0,
                "from_slew": 0.034233,
                "to_slew": 0.034233,
                "wire_delay": 0.0
            },
            "edge_1": {
                "wire_from_node": "dpath/b_reg/_023_:620255",
                "wire_to_node": "dpath/b_reg/_023_:620259",
                "wire_R": 0.857142857142857,
                "wire_C": 4.6356008480000124e-05,
                "from_slew": 0.034233,
                "to_slew": 0.03423300041277886,
                "wire_delay": 2.361574937142857e-06
            },
            "edge_2": {
                "wire_from_node": "dpath/b_reg/_023_:620259",
                "wire_to_node": "dpath/b_reg/_023_:1194851",
                "wire_R": 0.0,
                "wire_C": 4.6356008480000124e-05,
                "from_slew": 0.03423300041277886,
                "to_slew": 0.03423300041277886,
                "wire_delay": 0.0
            },
            "edge_3": {
                "wire_from_node": "dpath/b_reg/_023_:1194851",
                "wire_to_node": "dpath/b_reg/_023_:1190027",
                "wire_R": 1.9285714285714286,
                "wire_C": 8.940737576000005e-05,
                "from_slew": 0.03423300041277886,
                "to_slew": 0.03423300078551593,
                "wire_delay": 5.051714224680001e-06
            },
            "edge_4": {
                "wire_from_node": "dpath/b_reg/_023_:1190027",
                "wire_to_node": "dpath/b_reg/_023_:615435",
                "wire_R": 0.0,
                "wire_C": 8.940737576000005e-05,
                "from_slew": 0.03423300078551593,
                "to_slew": 0.03423300078551593,
                "wire_delay": 0.0
            },
            "edge_5": {
                "wire_from_node": "dpath/b_reg/_023_:615435",
                "wire_to_node": "dpath/b_reg/_089_:A",
                "wire_R": 0.0,
                "wire_C": 0.0,
                "from_slew": 0.03423300078551593,
                "to_slew": 0.03423300078551593,
                "wire_delay": 0.0
            }
        }
    },
    {
        "node_6": {
            "Point": "dpath/b_reg/_089_:A (sky130_fd_sc_hs__buf_1)",
            "Capacitance": 0.00253,
            "slew": 0.030595,
            "trans_type": "fall"
        }
    },
    {
        "inst_arc_6": {
            "Incr": 0.064865
        }
    },
    {
        "node_7": {
            "Point": "dpath/b_reg/_089_:X (sky130_fd_sc_hs__buf_1)",
            "Capacitance": 0.0024571182368,
            "slew": 0.019353,
            "trans_type": "fall"
        }
    },
    {
        "net_arc_7": {
            "Incr": 1.5e-05,
            "edge_0": {
                "wire_from_node": "dpath/b_reg/_089_:X",
                "wire_to_node": "dpath/b_reg/_007_:617046",
                "wire_R": 0.0,
                "wire_C": 0.0,
                "from_slew": 0.019367,
                "to_slew": 0.019367,
                "wire_delay": 0.0
            },
            "edge_1": {
                "wire_from_node": "dpath/b_reg/_007_:617046",
                "wire_to_node": "dpath/b_reg/_007_:617064",
                "wire_R": 3.857142857142857,
                "wire_C": 0.00018872420816,
                "from_slew": 0.019367,
                "to_slew": 0.019367004506306257,
                "wire_delay": 8.749519824754287e-06
            },
            "edge_2": {
                "wire_from_node": "dpath/b_reg/_007_:617064",
                "wire_to_node": "dpath/b_reg/_007_:1191656",
                "wire_R": 0.0,
                "wire_C": 0.00018872420816,
                "from_slew": 0.019367004506306257,
                "to_slew": 0.019367004506306257,
                "wire_delay": 0.0
            },
            "edge_3": {
                "wire_from_node": "dpath/b_reg/_007_:1191656",
                "wire_to_node": "dpath/b_reg/_007_:1183080",
                "wire_R": 3.428571428571428,
                "wire_C": 0.00015483491023999987,
                "from_slew": 0.019367004506306257,
                "to_slew": 0.019367005630706462,
                "wire_delay": 6.599433977965714e-06
            },
            "edge_4": {
                "wire_from_node": "dpath/b_reg/_007_:1183080",
                "wire_to_node": "dpath/b_reg/_007_:608488",
                "wire_R": 0.0,
                "wire_C": 0.0001548349102400001,
                "from_slew": 0.019367005630706462,
                "to_slew": 0.019367005630706462,
                "wire_delay": 0.0
            },
            "edge_5": {
                "wire_from_node": "dpath/b_reg/_007_:608488",
                "wire_to_node": "dpath/b_reg/_133_:D",
                "wire_R": 0.0,
                "wire_C": 0.0,
                "from_slew": 0.019367005630706462,
                "to_slew": 0.019367005630706462,
                "wire_delay": 0.0
            }
        }
    },
    {
        "node_8": {
            "Point": "dpath/b_reg/_133_:D (sky130_fd_sc_hs__dfxtp_1)",
            "Capacitance": 0.00177,
            "slew": 0.019353,
            "trans_type": "fall"
        }
    }
]
