{
    "id": 588,
    "name": "dpath/sub/_088_",
    "feature": {
        "llx": 76800,
        "lly": 47040,
        "urx": 81840,
        "ury": 55920,
        "wire_len": 13920,
        "via_num": 4,
        "drc_num": 0,
        "drc_type": [],
        "R": 24.857142857142854,
        "C": 0.00355041241344,
        "power": 2.633832841977098e-07,
        "delay": 0.037047108979199994,
        "slew": 0.013599036220314671,
        "aspect_ratio": 2,
        "width": 5040,
        "height": 8880,
        "area": 44755200,
        "volume": 89510400,
        "layer_ratio": [
            0.0,
            0.0,
            0.3400000035762787,
            0.0,
            0.6600000262260437,
            0.0,
            0.0,
            0.0,
            0.0,
            0.0,
            0.0
        ],
        "place_feature": {
            "pin_num": 2,
            "aspect_ratio": 2,
            "width": 4589,
            "height": 7736,
            "area": 35500504,
            "l_ness": 1.0,
            "hpwl": 12325,
            "rsmt": 12325
        }
    },
    "pin_num": 2,
    "pins": [
        {
            "id": 1542,
            "i": "dpath/sub/_152_",
            "p": "X",
            "driver": 1
        },
        {
            "id": 1543,
            "i": "dpath/sub/_154_",
            "p": "A",
            "driver": 0
        }
    ],
    "wire_num": 7,
    "wires": [
        {
            "id": 6004,
            "feature": {
                "wire_width": 140,
                "wire_len": 4320,
                "wire_density": null,
                "drc_num": 0,
                "R": 3.8571428571428577,
                "C": 0.00018872420816,
                "power": 7.777938629925714e-06,
                "delay": 0.009985079088617142,
                "slew": 1.2533535251324501e-09,
                "congestion": 4.0,
                "drc_type": []
            },
            "wire": {
                "id1": 699800,
                "x1": 76800,
                "y1": 55920,
                "real_x1": 76990,
                "real_y1": 56025,
                "r1": 233,
                "c1": 320,
                "l1": 2,
                "p1": -1,
                "id2": 699818,
                "x2": 81120,
                "y2": 55920,
                "real_x2": 81120,
                "real_y2": 56025,
                "r2": 233,
                "c2": 338,
                "l2": 2,
                "p2": -1
            },
            "path_num": 1,
            "paths": [
                {
                    "id1": 699800,
                    "x1": 76800,
                    "y1": 55920,
                    "real_x1": 76990,
                    "real_y1": 56025,
                    "r1": 233,
                    "c1": 320,
                    "l1": 2,
                    "p1": -1,
                    "id2": 699818,
                    "x2": 81120,
                    "y2": 55920,
                    "real_x2": 81120,
                    "real_y2": 56025,
                    "r2": 233,
                    "c2": 338,
                    "l2": 2,
                    "p2": -1
                }
            ],
            "patch_num": 2,
            "patchs": [
                377,
                378
            ]
        },
        {
            "id": 6005,
            "feature": {
                "wire_width": 140,
                "wire_len": 480,
                "wire_density": null,
                "drc_num": 0,
                "R": 0.4285714285714285,
                "C": 2.601769423999983e-05,
                "power": 1.07227382784578e-06,
                "delay": 0.0015104548796571425,
                "slew": 1.1711413644421853e-09,
                "congestion": 6.5,
                "drc_type": []
            },
            "wire": {
                "id1": 679987,
                "x1": 81360,
                "y1": 47040,
                "real_x1": 81360,
                "real_y1": 47135,
                "r1": 196,
                "c1": 339,
                "l1": 2,
                "p1": -1,
                "id2": 679989,
                "x2": 81840,
                "y2": 47040,
                "real_x2": 81855,
                "real_y2": 47135,
                "r2": 196,
                "c2": 341,
                "l2": 2,
                "p2": -1
            },
            "path_num": 1,
            "paths": [
                {
                    "id1": 679987,
                    "x1": 81360,
                    "y1": 47040,
                    "real_x1": 81360,
                    "real_y1": 47135,
                    "r1": 196,
                    "c1": 339,
                    "l1": 2,
                    "p1": -1,
                    "id2": 679989,
                    "x2": 81840,
                    "y2": 47040,
                    "real_x2": 81855,
                    "real_y2": 47135,
                    "r2": 196,
                    "c2": 341,
                    "l2": 2,
                    "p2": -1
                }
            ],
            "patch_num": 1,
            "patchs": [
                318
            ]
        },
        {
            "id": 6006,
            "feature": {
                "wire_width": 0,
                "wire_len": 0,
                "wire_density": 0.0,
                "drc_num": 0,
                "R": 0.0,
                "C": 2.601769423999983e-05,
                "power": 1.0722738278458072e-06,
                "delay": 0.0,
                "slew": 0.0,
                "congestion": 0.0,
                "drc_type": []
            },
            "wire": {
                "id1": 679987,
                "x1": 81360,
                "y1": 47040,
                "real_x1": 81360,
                "real_y1": 47135,
                "r1": 196,
                "c1": 339,
                "l1": 2,
                "p1": -1,
                "id2": 1254579,
                "x2": 81360,
                "y2": 47040,
                "real_x2": 81360,
                "real_y2": 47135,
                "r2": 196,
                "c2": 339,
                "l2": 4,
                "p2": -1,
                "via": 5
            },
            "path_num": 1,
            "paths": [
                {
                    "id1": 679987,
                    "x1": 81360,
                    "y1": 47040,
                    "real_x1": 81360,
                    "real_y1": 47135,
                    "r1": 196,
                    "c1": 339,
                    "l1": 2,
                    "p1": -1,
                    "id2": 1254579,
                    "x2": 81360,
                    "y2": 47040,
                    "real_x2": 81360,
                    "real_y2": 47135,
                    "r2": 196,
                    "c2": 339,
                    "l2": 4,
                    "p2": -1,
                    "via": 5
                }
            ],
            "patch_num": 1,
            "patchs": [
                318
            ]
        },
        {
            "id": 6007,
            "feature": {
                "wire_width": 0,
                "wire_len": 0,
                "wire_density": 0.0,
                "drc_num": 0,
                "R": 0.0,
                "C": 0.0,
                "power": 0.0,
                "delay": 0.0,
                "slew": 0.0,
                "congestion": 0.0,
                "drc_type": []
            },
            "wire": {
                "id1": 105397,
                "x1": 81840,
                "y1": 47040,
                "real_x1": 81855,
                "real_y1": 47135,
                "r1": 196,
                "c1": 341,
                "l1": 0,
                "p1": 1542,
                "id2": 679989,
                "x2": 81840,
                "y2": 47040,
                "real_x2": 81855,
                "real_y2": 47135,
                "r2": 196,
                "c2": 341,
                "l2": 2,
                "p2": -1,
                "via": 0
            },
            "path_num": 1,
            "paths": [
                {
                    "id1": 105397,
                    "x1": 81840,
                    "y1": 47040,
                    "real_x1": 81855,
                    "real_y1": 47135,
                    "r1": 196,
                    "c1": 341,
                    "l1": 0,
                    "p1": 1542,
                    "id2": 679989,
                    "x2": 81840,
                    "y2": 47040,
                    "real_x2": 81855,
                    "real_y2": 47135,
                    "r2": 196,
                    "c2": 341,
                    "l2": 2,
                    "p2": -1,
                    "via": 0
                }
            ],
            "patch_num": 1,
            "patchs": [
                318
            ]
        },
        {
            "id": 6008,
            "feature": {
                "wire_width": 0,
                "wire_len": 0,
                "wire_density": 0.0,
                "drc_num": 0,
                "R": 0.0,
                "C": 0.00018872420816,
                "power": 7.777938629925727e-06,
                "delay": 0.0,
                "slew": 0.0,
                "congestion": 0.0,
                "drc_type": []
            },
            "wire": {
                "id1": 125208,
                "x1": 76800,
                "y1": 55920,
                "real_x1": 76990,
                "real_y1": 56025,
                "r1": 233,
                "c1": 320,
                "l1": 0,
                "p1": 1543,
                "id2": 699800,
                "x2": 76800,
                "y2": 55920,
                "real_x2": 76990,
                "real_y2": 56025,
                "r2": 233,
                "c2": 320,
                "l2": 2,
                "p2": -1,
                "via": 0
            },
            "path_num": 1,
            "paths": [
                {
                    "id1": 125208,
                    "x1": 76800,
                    "y1": 55920,
                    "real_x1": 76990,
                    "real_y1": 56025,
                    "r1": 233,
                    "c1": 320,
                    "l1": 0,
                    "p1": 1543,
                    "id2": 699800,
                    "x2": 76800,
                    "y2": 55920,
                    "real_x2": 76990,
                    "real_y2": 56025,
                    "r2": 233,
                    "c2": 320,
                    "l2": 2,
                    "p2": -1,
                    "via": 0
                }
            ],
            "patch_num": 1,
            "patchs": [
                377
            ]
        },
        {
            "id": 6009,
            "feature": {
                "wire_width": 0,
                "wire_len": 0,
                "wire_density": 0.0,
                "drc_num": 0,
                "R": 0.0,
                "C": 0.0003604643043200002,
                "power": 1.4855906746753371e-05,
                "delay": 0.0,
                "slew": 0.0,
                "congestion": 0.0,
                "drc_type": []
            },
            "wire": {
                "id1": 699818,
                "x1": 81120,
                "y1": 55920,
                "real_x1": 81120,
                "real_y1": 56025,
                "r1": 233,
                "c1": 338,
                "l1": 2,
                "p1": -1,
                "id2": 1274410,
                "x2": 81120,
                "y2": 55920,
                "real_x2": 81120,
                "real_y2": 56025,
                "r2": 233,
                "c2": 338,
                "l2": 4,
                "p2": -1,
                "via": 5
            },
            "path_num": 1,
            "paths": [
                {
                    "id1": 699818,
                    "x1": 81120,
                    "y1": 55920,
                    "real_x1": 81120,
                    "real_y1": 56025,
                    "r1": 233,
                    "c1": 338,
                    "l1": 2,
                    "p1": -1,
                    "id2": 1274410,
                    "x2": 81120,
                    "y2": 55920,
                    "real_x2": 81120,
                    "real_y2": 56025,
                    "r2": 233,
                    "c2": 338,
                    "l2": 4,
                    "p2": -1,
                    "via": 5
                }
            ],
            "patch_num": 1,
            "patchs": [
                378
            ]
        },
        {
            "id": 6010,
            "feature": {
                "wire_width": 140,
                "wire_len": 9120,
                "wire_density": 0.028528528528528527,
                "drc_num": 0,
                "R": 8.14285714285714,
                "C": 0.0003604643043200002,
                "power": 1.4855906746753371e-05,
                "delay": 0.025551575010925708,
                "slew": 1.3499345627443482e-08,
                "congestion": -16.166666666666664,
                "drc_type": []
            },
            "wire": {
                "id1": 1254579,
                "x1": 81360,
                "y1": 47040,
                "real_x1": 81360,
                "real_y1": 47135,
                "r1": 196,
                "c1": 339,
                "l1": 4,
                "p1": -1,
                "id2": 1274410,
                "x2": 81120,
                "y2": 55920,
                "real_x2": 81120,
                "real_y2": 56025,
                "r2": 233,
                "c2": 338,
                "l2": 4,
                "p2": -1
            },
            "path_num": 3,
            "paths": [
                {
                    "id1": 1254579,
                    "x1": 81360,
                    "y1": 47040,
                    "real_x1": 81360,
                    "real_y1": 47135,
                    "r1": 196,
                    "c1": 339,
                    "l1": 4,
                    "p1": -1,
                    "id2": 1263155,
                    "x2": 81360,
                    "y2": 50880,
                    "real_x2": 81360,
                    "real_y2": 50880,
                    "r2": 212,
                    "c2": 339,
                    "l2": 4,
                    "p2": -1
                },
                {
                    "id1": 1263155,
                    "x1": 81360,
                    "y1": 50880,
                    "real_x1": 81360,
                    "real_y1": 50880,
                    "r1": 212,
                    "c1": 339,
                    "l1": 4,
                    "p1": -1,
                    "id2": 1263154,
                    "x2": 81120,
                    "y2": 50880,
                    "real_x2": 81120,
                    "real_y2": 50880,
                    "r2": 212,
                    "c2": 338,
                    "l2": 4,
                    "p2": -1
                },
                {
                    "id1": 1263154,
                    "x1": 81120,
                    "y1": 50880,
                    "real_x1": 81120,
                    "real_y1": 50880,
                    "r1": 212,
                    "c1": 338,
                    "l1": 4,
                    "p1": -1,
                    "id2": 1274410,
                    "x2": 81120,
                    "y2": 55920,
                    "real_x2": 81120,
                    "real_y2": 56025,
                    "r2": 233,
                    "c2": 338,
                    "l2": 4,
                    "p2": -1
                }
            ],
            "patch_num": 3,
            "patchs": [
                318,
                348,
                378
            ]
        }
    ],
    "routing_graph": {
        "vertices": [
            {
                "id": 0,
                "is_pin": 0,
                "is_driver_pin": 0,
                "x": 76990,
                "y": 56025,
                "layer_id": 2
            },
            {
                "id": 1,
                "is_pin": 0,
                "is_driver_pin": 0,
                "x": 81120,
                "y": 56025,
                "layer_id": 2
            },
            {
                "id": 2,
                "is_pin": 0,
                "is_driver_pin": 0,
                "x": 81360,
                "y": 47135,
                "layer_id": 4
            },
            {
                "id": 3,
                "is_pin": 0,
                "is_driver_pin": 0,
                "x": 81360,
                "y": 47135,
                "layer_id": 2
            },
            {
                "id": 4,
                "is_pin": 0,
                "is_driver_pin": 0,
                "x": 81855,
                "y": 47135,
                "layer_id": 2
            },
            {
                "id": 5,
                "is_pin": 1,
                "is_driver_pin": 1,
                "x": 81855,
                "y": 47135,
                "layer_id": 0
            },
            {
                "id": 6,
                "is_pin": 1,
                "is_driver_pin": 0,
                "x": 76990,
                "y": 56025,
                "layer_id": 0
            },
            {
                "id": 7,
                "is_pin": 0,
                "is_driver_pin": 0,
                "x": 81120,
                "y": 56025,
                "layer_id": 4
            }
        ],
        "edges": [
            {
                "source_id": 0,
                "target_id": 1,
                "path": [
                    {
                        "x": 76990,
                        "y": 56025,
                        "layer_id": 2
                    },
                    {
                        "x": 81120,
                        "y": 56025,
                        "layer_id": 2
                    }
                ]
            },
            {
                "source_id": 3,
                "target_id": 4,
                "path": [
                    {
                        "x": 81360,
                        "y": 47135,
                        "layer_id": 2
                    },
                    {
                        "x": 81855,
                        "y": 47135,
                        "layer_id": 2
                    }
                ]
            },
            {
                "source_id": 3,
                "target_id": 2,
                "path": [
                    {
                        "x": 81360,
                        "y": 47135,
                        "layer_id": 2
                    },
                    {
                        "x": 81360,
                        "y": 47135,
                        "layer_id": 4
                    }
                ]
            },
            {
                "source_id": 5,
                "target_id": 4,
                "path": [
                    {
                        "x": 81855,
                        "y": 47135,
                        "layer_id": 0
                    },
                    {
                        "x": 81855,
                        "y": 47135,
                        "layer_id": 2
                    }
                ]
            },
            {
                "source_id": 6,
                "target_id": 0,
                "path": [
                    {
                        "x": 76990,
                        "y": 56025,
                        "layer_id": 0
                    },
                    {
                        "x": 76990,
                        "y": 56025,
                        "layer_id": 2
                    }
                ]
            },
            {
                "source_id": 1,
                "target_id": 7,
                "path": [
                    {
                        "x": 81120,
                        "y": 56025,
                        "layer_id": 2
                    },
                    {
                        "x": 81120,
                        "y": 56025,
                        "layer_id": 4
                    }
                ]
            },
            {
                "source_id": 2,
                "target_id": 7,
                "path": [
                    {
                        "x": 81360,
                        "y": 47135,
                        "layer_id": 4
                    },
                    {
                        "x": 81360,
                        "y": 50880,
                        "layer_id": 4
                    },
                    {
                        "x": 81120,
                        "y": 50880,
                        "layer_id": 4
                    },
                    {
                        "x": 81120,
                        "y": 56025,
                        "layer_id": 4
                    }
                ]
            }
        ]
    }
}